emergency_simulation/__init__.py
emergency_simulation-1.0.0.dist-info/LICENSE
emergency_simulation-1.0.0.dist-info/WHEEL
emergency_simulation-1.0.0.dist-info/METADATA
emergency_simulation-1.0.0.dist-info/RECORD
