Metadata-Version: 2.1
Name: emergency_simulation
Version: 1.0.0
Summary: Emergency Response Simulation
Home-page: https://github.com/luccabb/emergency_simulation
Author: Lucca Bertoncini
Author-email: luccabazzo@gmail.com
Requires-Python: >=3.8.2
Classifier: License :: OSI Approved :: MIT License
